aio_send_dir/__init__.py
aio_send_dir/v1.py
aio_send_dir-0.1.3.dist-info/LICENSE
aio_send_dir-0.1.3.dist-info/METADATA
aio_send_dir-0.1.3.dist-info/WHEEL
aio_send_dir-0.1.3.dist-info/RECORD
